unpast/__init__.py
unpast/core/__init__.py
unpast/core/binarization.py
unpast/core/feature_clustering.py
unpast/core/preprocessing.py
unpast/core/sample_clustering.py
unpast/misc/consensus.py
unpast/misc/eval.py
unpast/misc/unpast_DE.py
unpast/rscripts/add_genes.R
unpast/rscripts/run_WGCNA.R
unpast/run_unpast.py
unpast/setup.py
unpast/tests/core/test_binarization.py
unpast/tests/core/test_feature_clustering.py
unpast/tests/core/test_preprocessing.py
unpast/tests/core/test_sample_clustering.py
unpast/tests/misc/test_eval.py
unpast/tests/results/runs/run_test_clear_biclusters/args.tsv
unpast/tests/results/runs/run_test_clear_biclusters/biclusters.tsv
unpast/tests/results/runs/run_test_clear_biclusters/binarization/bin_args.tsv
unpast/tests/results/runs/run_test_clear_biclusters/binarization/bin_background.tsv
unpast/tests/results/runs/run_test_clear_biclusters/binarization/bin_res.tsv
unpast/tests/results/runs/run_test_clear_biclusters/binarization/bin_stats.tsv
unpast/tests/results/runs/run_test_clear_biclusters/tmp_wgcna/wgcna_20250716T095858.tsv
unpast/tests/results/runs/run_test_reproducible_louvain/args.tsv
unpast/tests/results/runs/run_test_reproducible_louvain/biclusters.tsv
unpast/tests/results/runs/run_test_reproducible_louvain/binarization/bin_args.tsv
unpast/tests/results/runs/run_test_reproducible_louvain/binarization/bin_background.tsv
unpast/tests/results/runs/run_test_reproducible_louvain/binarization/bin_res.tsv
unpast/tests/results/runs/run_test_reproducible_louvain/binarization/bin_stats.tsv
unpast/tests/results/runs/run_test_reproducible_wgcna/args.tsv
unpast/tests/results/runs/run_test_reproducible_wgcna/biclusters.tsv
unpast/tests/results/runs/run_test_reproducible_wgcna/binarization/bin_args.tsv
unpast/tests/results/runs/run_test_reproducible_wgcna/binarization/bin_background.tsv
unpast/tests/results/runs/run_test_reproducible_wgcna/binarization/bin_res.tsv
unpast/tests/results/runs/run_test_reproducible_wgcna/binarization/bin_stats.tsv
unpast-0.1.11.dist-info/LICENSE
unpast-0.1.11.dist-info/METADATA
unpast-0.1.11.dist-info/WHEEL
unpast-0.1.11.dist-info/entry_points.txt
unpast-0.1.11.dist-info/RECORD
