Metadata-Version: 2.3
Name: unpast
Version: 0.1.11
Summary: A novel method for unsupervised patient stratification.
License: GPL-3.0
Author: Olga Zolotareva (ozolotareva)
Maintainer: Olga Zolotareva (ozolotareva)
Requires-Python: >=3.9,<3.12
Classifier: License :: OSI Approved :: GNU General Public License v3 (GPLv3)
Classifier: Programming Language :: Python :: 3
Classifier: Programming Language :: Python :: 3.9
Classifier: Programming Language :: Python :: 3.10
Classifier: Programming Language :: Python :: 3.11
Requires-Dist: fisher (>=0.1.12,<=0.1.14)
Requires-Dist: kneed (>=0.8.5,<0.9.0)
Requires-Dist: lifelines (>=0.27.4,<=0.30.0)
Requires-Dist: matplotlib (>=3.7.1,<4.0.0)
Requires-Dist: numpy (>=1.25,<2.0.0)
Requires-Dist: pandas (>=1.5,<=2.3.1)
Requires-Dist: pytest (>=8.3.3,<9.0.0)
Requires-Dist: scikit-learn (>=1.3.0,<=1.6.1)
Requires-Dist: scikit-network (>=0.29.0,<=0.33.3)
Requires-Dist: scipy (>=1.7.2,<1.13.1)
Requires-Dist: seaborn (>=0.11.1)
Requires-Dist: statsmodels (>=0.14,<0.15)
Project-URL: Repository, https://github.com/ozolotareva/unpast
